Bing/__init__.py
Bing/bing.py
Bing/cli.py
tests/__init__.py
tests/bing_test.py
gen_bing-0.0.9.dist-info/LICENSE
gen_bing-0.0.9.dist-info/METADATA
gen_bing-0.0.9.dist-info/WHEEL
gen_bing-0.0.9.dist-info/entry_points.txt
gen_bing-0.0.9.dist-info/top_level.txt
gen_bing-0.0.9.dist-info/RECORD
