Metadata-Version: 2.2
Name: gen_bing
Version: 0.0.9
Summary: I'm From Indonesian, and I'm still learning.
Author: Lucifer
Author-email: ikyodeos01@gmail.com
Keywords: bing image generator gabut
Classifier: Intended Audience :: Developers
Classifier: Topic :: Software Development :: Libraries :: Python Modules
Classifier: Programming Language :: Python :: 3.9
Classifier: Programming Language :: Python :: 3.10
Classifier: Programming Language :: Python :: 3.11
Classifier: License :: OSI Approved :: MIT License
Classifier: Operating System :: OS Independent
Requires-Python: >=3.9
License-File: LICENSE
Requires-Dist: aiofiles==24.1.0
Requires-Dist: httpx[http2]
Requires-Dist: aiohttp>=3.9.5
Dynamic: author
Dynamic: author-email
Dynamic: classifier
Dynamic: description
Dynamic: description-content-type
Dynamic: keywords
Dynamic: requires-dist
Dynamic: requires-python
Dynamic: summary
